OutbreakPAD/Detection.py
OutbreakPAD/Detection2.py
OutbreakPAD/Detection3.py
OutbreakPAD/PAD.py
OutbreakPAD/PredictionDetection.py
OutbreakPAD/Preprocessed_data.py
OutbreakPAD/__init__.py
OutbreakPAD/Detection_Methods/Buishand_U_change_point_detection.py
OutbreakPAD/Detection_Methods/CUSUM.py
OutbreakPAD/Detection_Methods/EWMA.py
OutbreakPAD/Detection_Methods/Kendall_change_point_detection.py
OutbreakPAD/Detection_Methods/Pettitt_change_point_detection.py
OutbreakPAD/Detection_Methods/Pvalue_CUSUM.py
OutbreakPAD/Detection_Methods/SNHT_change_point_detection.py
OutbreakPAD/Detection_Methods/__init__.py
OutbreakPAD/Detection_Methods/pyspc/__init__.py
OutbreakPAD/Detection_Methods/pyspc/pyspc.py
OutbreakPAD/Detection_Methods/pyspc/results.py
OutbreakPAD/Detection_Methods/pyspc/rules.py
OutbreakPAD/Detection_Methods/pyspc/ccharts/__init__.py
OutbreakPAD/Detection_Methods/pyspc/ccharts/ccharts.py
OutbreakPAD/Detection_Methods/pyspc/ccharts/cusum.py
OutbreakPAD/Detection_Methods/pyspc/ccharts/ewma.py
OutbreakPAD/Detection_Methods/pyspc/ccharts/tables.py
OutbreakPAD/Prediction/ARIMA_Find_Parameter.py
OutbreakPAD/Prediction/ARIMA_GRNN_Pre.py
OutbreakPAD/Prediction/ARIMA_Pre.py
OutbreakPAD/Prediction/Find_best_smoothing_factor.py
OutbreakPAD/Prediction/GRNN_Model.py
OutbreakPAD/Prediction/GRNN_Predict_Model.py
OutbreakPAD/Prediction/__init__.py
OutbreakPAD/Prediction/outbreak_prediction.py
OutbreakPAD/Prediction/read_data.py
OutbreakPAD/data/__init__.py
OutbreakPAD/exampledata/__init__.py
OutbreakPAD/exampledata/example.csv
tests/OutbreakPAD_test.py
OutbreakPAD-1.0.dist-info/LICENSE
OutbreakPAD-1.0.dist-info/METADATA
OutbreakPAD-1.0.dist-info/WHEEL
OutbreakPAD-1.0.dist-info/top_level.txt
OutbreakPAD-1.0.dist-info/RECORD
