Metadata-Version: 2.1
Name: OutbreakPAD
Version: 1.0
Summary: This is a script of outbreak prediction
Home-page: https://github.com/FengYe-Lab/OutbreakPAD
Author: Zou
Author-email: 21818662@zju.edu.cn
License: GPLv3
Keywords: Outbreak Prediction subscripe
Platform: UNKNOWN
Classifier: Operating System :: Microsoft :: Windows
Classifier: Operating System :: POSIX :: Linux
Classifier: Operating System :: MacOS
Classifier: Programming Language :: Python :: 3.3
Classifier: Programming Language :: Python :: 3.4
Classifier: Programming Language :: Python :: 3.5
Classifier: Topic :: Software Development :: Libraries :: Python Modules
Requires-Dist: numpy (>=1.7.0)
Requires-Dist: scipy
Requires-Dist: pandas
Requires-Dist: statsmodels
Requires-Dist: tensorflow
Requires-Dist: neupy
Requires-Dist: scikit-learn (>=0.16.1)
Requires-Dist: matplotlib (>=1.3.0)
